Workbook

Sheet Instructions
A1: MS Excel Practical Exam
A2: Total Questions: 30
A3: Difficulty Level: Medium
A4: Syllabus: Formulas, Logical Functions, Lookups, INDEX-MATCH, Pivot Tables & Charts, Data Analysis
A5: Attempt all questions using appropriate Excel tools/functions.

Sheet Sales_Data
A1: Order_ID | B1: Region | C1: Salesperson | D1: Product | E1: Quantity | F1: Unit_Price | G1: Sales_Date
A2: 301 | B2: North | C2: Amit | D2: Laptop | E2: 2 | F2: 45000 | G2: 05-01-2025
A3: 302 | B3: South | C3: Riya | D3: Mobile | E3: 5 | F3: 15000 | G3: 07-01-2025
A4: 303 | B4: East | C4: Kunal | D4: Tablet | E4: 3 | F4: 18000 | G4: 10-01-2025
A5: 304 | B5: West | C5: Neha | D5: Laptop | E5: 1 | F5: 45000 | G5: 12-01-2025
A6: 305 | B6: North | C6: Amit | D6: Mobile | E6: 4 | F6: 15000 | G6: 15-01-2025
A7: 306 | B7: South | C7: Riya | D7: Laptop | E7: 2 | F7: 45000 | G7: 18-01-2025

Sheet Product_Master
A1: Product | B1: Category | C1: GST_%
A2: Laptop | B2: Electronics | C2: 18
A3: Mobile | B3: Electronics | C3: 12
A4: Tablet | B4: Electronics | C4: 12

Sheet Student_Marks
A1: Student_ID | B1: Name | C1: Maths | D1: Statistics | E1: Excel | F1: Attendance_%
A2: 1 | B2: Rahul | C2: 78 | D2: 82 | E2: 85 | F2: 92
A3: 2 | B3: Sneha | C3: 88 | D3: 91 | E3: 90 | F3: 96
A4: 3 | B4: Arjun | C4: 65 | D4: 70 | E4: 72 | F4: 85
A5: 4 | B5: Pooja | C5: 92 | D5: 89 | E5: 94 | F5: 98
A6: 5 | B6: Vikas | C6: 55 | D6: 60 | E6: 58 | F6: 80

Sheet Questions
A1: 1. Calculate Total Sales for each order (Quantity × Unit_Price). | J1: 2
A2: 2. Calculate GST Amount using VLOOKUP from Product_Master. | J2: 2
A3: 3. Find Final Amount payable (Total Sales + GST). | J3: 2
A4: 4. Find Grand Total of Final Amount. | J4: 2
A5: 5. Count total number of orders using COUNTA. | J5: 2
A6: 6. Find Region-wise total sales using SUMIF. | J6: 2
A7: 7. Use IF to classify Quantity as High (>3) or Low (<=3). | J7: 2
A8: 8. Find the maximum and minimum Final Amount. | J8: 2
A9: 9. Extract month name from Sales_Date. | J9: 2
A10: 10. Sort Sales_Data by Final Amount (Descending). | J10: 2
A11: 11. Use INDEX-MATCH to fetch Product Category. | J11: 2
A12: 12. Calculate average marks of each student. | J12: 2
... A30: 30. Protect the Student_Marks sheet. | J30: 2
J32: =SUM(J1:J30) -> 60

Sheet Sheet1
A1: 1
A2: Quantity | B2: Unit_Price | C2: total sale | D2: Product
A3: 2 | B3: 45000 | C3: =SUM(A3*B3) -> 90000 | D3: Laptop
A4: 5 | B4: 15000 | C4: =SUM(A4*B4) -> 75000 | D4: Mobile
A5: 3 | B5: 18000 | C5: =SUM(A5*B5) -> 54000 | D5: Tablet
A6: 1 | B6: 45000 | C6: =SUM(A6*B6) -> 45000 | D6: Laptop
A7: 4 | B7: 15000 | C7: =SUM(A7*B7) -> 60000 | D7: Mobile
A8: 2 | B8: 45000 | C8: =SUM(A8*B8) -> 90000 | D8: Laptop
A10: 2
A12: Product | B12: price | C12: GST_% | D12: gst amount | E12: gst
A13: Laptop | B13: 45000 | C13: 18 | D13: =B13*C13/100 -> 8100 | E13: =VLOOKUP(A13,Product_Master!A1:C4,3,FALSE) -> 18
A14: Mobile | B14: 15000 | C14: 12 | D14: =B14*C14/100 -> 1800
A15: Tablet | B15: 45000 | C15: 12 | D15: =B15*C15/100 -> 5400
A17: 3
A19: Product | B19: price | C19: GST_% | D19: sale+gst | E19: payble
A20: Laptop | B20: 45000 | C20: 18 | D20: =B20*C20/100 -> 8100 | E20: =B20+D20 -> 53100
A21: Mobile | B21: 15000 | C21: 12 | D21: =B21*C21/100 -> 1800 | E21: =B21+D21 -> 16800
A22: Tablet | B22: 18000 | C22: 12 | D22: =B22*C22/100 -> 2160 | E22: =B22+D22 -> 20160
A24: 4
A26: Product | B26: price
A27: Laptop | B27: 53100
A28: Mobile | B28: 16800
A29: Tablet | B29: 20160
A30: grand total | B30: =B27+B28+B29 -> 90060
A32: 5
A34: Order_ID | B34: total order
A35: 301 | B35: =COUNTA(A35:A40) -> 6
A36: 302
A37: 303
A38: 304
A39: 305
A40: 306
A42: 6
A44: Region | B44: total sale
A45: North | B45: 150000 | C45: =SUMIF($A$45:$A$48,B45,$B$45:$B$48) -> 0
A46: South | B46: 165000 | C46: =SUMIF($A$45:$A$48,B46,$B$45:$B$48) -> 0
A47: East | B47: 54000 | C47: =SUMIF($A$45:$A$48,B47,$B$45:$B$48) -> 0
A48: West | B48: 45000 | C48: =SUMIF($A$45:$A$48,B48,$B$45:$B$48) -> 0
A50: 7
A52: Quantity | B52: >3 | C52: <=3
A53: 2 | B53: =IF(Sheet1!A53>3,"low","high") -> high | C53: =IF(A53<=3,"low","high") -> low
A54: 5 | B54: =IF(Sheet1!A54>3,"low","high") -> low | C54: =IF(A54<=3,"low","high") -> high
A55: 3 | B55: =IF(Sheet1!A55>3,"low","high") -> high | C55: =IF(A55<=3,"low","high") -> low
A56: 1 | B56: =IF(Sheet1!A56>3,"low","high") -> high | C56: =IF(A56<=3,"low","high") -> low
A57: 4 | B57: =IF(Sheet1!A57>3,"low","high") -> low | C57: =IF(A57<=3,"low","high") -> high
A58: 2 | B58: =IF(Sheet1!A58>3,"low","high") -> high | C58: =IF(A58<=3,"low","high") -> low
A60: 8
A62: Region | B62: total sale | C62: maximum | D62: minimum
A63: North | B63: 150000 | C63: =MAX(A63:A66,B63:B66) -> 165000 | D63: =MIN(A63:A66,B63:B66) -> 45000
A64: South | B64: 165000
A65: East | B65: 54000
A66: West | B66: 45000
A69: 9
A71: Sales_Date | B71: month
A72: 05-01-2025 | B72: =TEXT(A72,"mmm") -> Jan
A73: 45754 | B73: =TEXT(A73,"mmm") -> Apr
A74: 10-01-2025 | B74: =TEXT(A74,"mmm") -> Jan
A75: 45700 | B75: =TEXT(A75,"mmm") -> Feb
A76: 15-01-2025 | B76: =TEXT(A76,"mmm") -> Jan
A77: 18-01-2025 | B77: =TEXT(A77,"mmm") -> Jan
A79: 10
A81: Order_ID | B81: Region | C81: Salesperson | D81: Product | E81: Quantity | F81: Unit_Price | G81: Sales_Date | H81: total sale
A82: 301 | B82: North | C82: Amit | D82: Laptop | E82: 2 | F82: 45000 | G82: 05-01-2025 | H82: 90000
A83: 306 | B83: South | C83: Riya | D83: Laptop | E83: 2 | F83: 45000 | G83: 18-01-2025 | H83: 90000
A84: 302 | B84: South | C84: Riya | D84: Mobile | E84: 5 | F84: 15000 | G84: 07-01-2025 | H84: 75000
A85: 305 | B85: North | C85: Amit | D85: Mobile | E85: 4 | F85: 15000 | G85: 15-01-2025 | H85: 60000
A86: 303 | B86: East | C86: Kunal | D86: Tablet | E86: 3 | F86: 18000 | G86: 10-01-2025 | H86: 54000
A87: 304 | B87: West | C87: Neha | D87: Laptop | E87: 1 | F87: 45000 | G87: 12-01-2025 | H87: 45000
A90: 11
A92: Product | B92: Category | C92: match
A93: Laptop | B93: Electronics
A94: Mobile | B94: Electronics
A95: Tablet | B95: Electronics
A97: 12
B99: Name | C99: Maths | D99: Statistics | E99: Excel | F99: Attendance_% | G99: avarage
A100: 1 | B100: Rahul | C100: 78 | D100: 82 | E100: 85 | F100: 92 | G100: =AVERAGE(C100,D100,E100) -> 81.666667
A101: 2 | B101: Sneha | C101: 88 | D101: 91 | E101: 90 | F101: 96 | G101: =AVERAGE(C101,D101,E101) -> 89.666667
A102: 3 | B102: Arjun | C102: 65 | D102: 70 | E102: 72 | F102: 85 | G102: =AVERAGE(C102,D102,E102) -> 69
A103: 4 | B103: Pooja | C103: 92 | D103: 89 | E103: 94 | F103: 98 | G103: =AVERAGE(C103,D103,E103) -> 91.666667
A104: 5 | B104: Vikas | C104: 55 | D104: 60 | E104: 58 | F104: 80 | G104: =AVERAGE(C104,D104,E104) -> 57.666667
A107: 13
A109: Name | B109: avarage | C109: topper
A110: Rahul | B110: 81.666667 | C110: =MAX(B110:B114,A110:A114) -> 91.666667
A111: Sneha | B111: 89.666667
A112: Arjun | B112: 69
A113: Pooja | B113: 91.666667
A114: Vikas | B114: 57.666667
A116: 14
